tai_chi_tuna/__init__.py
tai_chi_tuna/config.py
tai_chi_tuna/utils.py
tai_chi_tuna/flow/__init__.py
tai_chi_tuna/flow/to_enrich.py
tai_chi_tuna/flow/to_quantify.py
tai_chi_tuna/flow/to_train.py
tai_chi_tuna/flow/trunk.py
tai_chi_tuna/flow/to_model/__init__.py
tai_chi_tuna/flow/to_model/batching.py
tai_chi_tuna/flow/to_model/nn_parts.py
tai_chi_tuna/flow/to_model/optimizing.py
tai_chi_tuna/flow/to_model/widgeting.py
tai_chi_tuna/front/__init__.py
tai_chi_tuna/front/html.py
tai_chi_tuna/front/structure.py
tai_chi_tuna/front/teacher.py
tai_chi_tuna/front/typer.py
tai_chi_tuna/front/widget.py
tai_chi_tuna/static/README.md
tai_chi_tuna/static/img/README.md
tai_chi_tuna/static/img/step1_enrich.jpg
tai_chi_tuna/static/img/step2_quantify.jpg
tai_chi_tuna/static/img/step3_modeling.jpg
tai_chi_tuna/static/img/step4_training.jpg
tai_chi_tuna/static/teacher/README.md
tai_chi_tuna/static/teacher/step1_enrich.html
tai_chi_tuna/static/teacher/step2_quantify.html
tai_chi_tuna/static/teacher/step3_modeling.html
tai_chi_tuna/static/teacher/step4_training.html
tai_chi_tuna-0.1.2.dist-info/LICENSE
tai_chi_tuna-0.1.2.dist-info/METADATA
tai_chi_tuna-0.1.2.dist-info/WHEEL
tai_chi_tuna-0.1.2.dist-info/top_level.txt
tai_chi_tuna-0.1.2.dist-info/RECORD
